LICENSE
README.md
setup.py
psbt_faker/__init__.py
psbt_faker/base58.py
psbt_faker/bip32.py
psbt_faker/ctransaction.py
psbt_faker/helpers.py
psbt_faker/multisig.py
psbt_faker/psbt.py
psbt_faker/ripemd.py
psbt_faker/segwit_addr.py
psbt_faker/serialize.py
psbt_faker/txn.py
psbt_faker.egg-info/PKG-INFO
psbt_faker.egg-info/SOURCES.txt
psbt_faker.egg-info/dependency_links.txt
psbt_faker.egg-info/entry_points.txt
psbt_faker.egg-info/requires.txt
psbt_faker.egg-info/top_level.txt