Metadata-Version: 2.1
Name: psbt-faker
Version: 1.4
Summary: Constructs a valid PSBT files which spend non-existant BTC to random addresses
Home-page: https://github.com/Coldcard/psbt_faker
Author: Coinkite Inc.
Author-email: support@coinkite.com
License: UNKNOWN
Platform: UNKNOWN
Classifier: Programming Language :: Python :: 3
Classifier: License :: OSI Approved :: MIT License
Classifier: Operating System :: OS Independent
Requires-Python: >3.6.0
License-File: LICENSE
